readme_ready/__init__.py
readme_ready/__main__.py
readme_ready/base.py
readme_ready/main.py
readme_ready/types.py
readme_ready/index/__init__.py
readme_ready/index/convert_json_to_markdown.py
readme_ready/index/create_vector_store.py
readme_ready/index/index.py
readme_ready/index/process_repository.py
readme_ready/index/prompts.py
readme_ready/index/select_model.py
readme_ready/query/__init__.py
readme_ready/query/create_chat_chain.py
readme_ready/query/query.py
readme_ready/utils/HNSWLib.py
readme_ready/utils/__init__.py
readme_ready/utils/file_utils.py
readme_ready/utils/llm_utils.py
readme_ready/utils/traverse_file_system.py
readme_ready-1.1.5.dist-info/licenses/LICENSE
readme_ready-1.1.5.dist-info/METADATA
readme_ready-1.1.5.dist-info/WHEEL
readme_ready-1.1.5.dist-info/entry_points.txt
readme_ready-1.1.5.dist-info/top_level.txt
readme_ready-1.1.5.dist-info/RECORD
