Metadata-Version: 2.4
Name: readme_ready
Version: 1.1.5
Summary: Auto-generate code documentation in Markdown format in seconds.
Home-page: https://github.com/souradipp76/ReadMeReady/
Author: souradipp76
License-File: LICENSE
Requires-Dist: torch
Requires-Dist: langchain
Requires-Dist: markdown2
Requires-Dist: langchain_openai
Requires-Dist: langchain_experimental
Requires-Dist: langchain_huggingface
Requires-Dist: hnswlib
Requires-Dist: questionary
Requires-Dist: accelerate
Requires-Dist: bitsandbytes
Requires-Dist: optimum
Requires-Dist: auto-gptq; sys_platform != "darwin"
Requires-Dist: python-magic
Requires-Dist: mkdocstrings-python
Requires-Dist: sentencepiece
Requires-Dist: sentence_transformers
Requires-Dist: pymarkdownlnt
Requires-Dist: peft
Requires-Dist: gguf
Provides-Extra: test
Requires-Dist: pytest; extra == "test"
Requires-Dist: coverage; extra == "test"
Requires-Dist: flake8; extra == "test"
Requires-Dist: black; extra == "test"
Requires-Dist: isort; extra == "test"
Requires-Dist: pytest-cov; extra == "test"
Requires-Dist: mypy; extra == "test"
Requires-Dist: gitchangelog; extra == "test"
Requires-Dist: mkdocs; extra == "test"
Requires-Dist: pymdown-extensions; extra == "test"
Requires-Dist: callouts; extra == "test"
Dynamic: author
Dynamic: description
Dynamic: description-content-type
Dynamic: home-page
Dynamic: license-file
Dynamic: provides-extra
Dynamic: requires-dist
Dynamic: summary
